setup.py
robosense/__init__.py
robosense/general.py
robosense/globlvar1.py
robosense/globlvar10.py
robosense/globlvar2.py
robosense/globlvar3.py
robosense/globlvar4.py
robosense/globlvar5.py
robosense/globlvar6.py
robosense/globlvar7.py
robosense/globlvar8.py
robosense/globlvar9.py
robosense/winprint.py
robosense.egg-info/PKG-INFO
robosense.egg-info/SOURCES.txt
robosense.egg-info/dependency_links.txt
robosense.egg-info/top_level.txt