Metadata-Version: 2.1
Name: robosense
Version: 0.0.6
Summary: robosense lib
Home-page: https://github.com/robosense
Author: Wenjie Zheng
Author-email: wjzheng@robosense.cn
License: MIT Licence
Keywords: pip,robosense
Platform: any
Classifier: Programming Language :: Python :: 3
Classifier: License :: OSI Approved :: MIT License
Classifier: Operating System :: OS Independent
Requires-Python: >=3.6
